nidaqmx/__init__.py
nidaqmx/__main__.py
nidaqmx/_base_interpreter.py
nidaqmx/_bitfield_utils.py
nidaqmx/_dotenvpath.py
nidaqmx/_feature_toggles.py
nidaqmx/_grpc_interpreter.py
nidaqmx/_grpc_time.py
nidaqmx/_install_daqmx.py
nidaqmx/_installer_metadata.json
nidaqmx/_lib.py
nidaqmx/_lib_time.py
nidaqmx/_library_interpreter.py
nidaqmx/_linux_installation_commands.py
nidaqmx/_stubs/__init__.py
nidaqmx/_stubs/data_moniker_pb2.py
nidaqmx/_stubs/data_moniker_pb2.pyi
nidaqmx/_stubs/data_moniker_pb2_grpc.py
nidaqmx/_stubs/data_moniker_pb2_grpc.pyi
nidaqmx/_stubs/nidaqmx_pb2.py
nidaqmx/_stubs/nidaqmx_pb2.pyi
nidaqmx/_stubs/nidaqmx_pb2_grpc.py
nidaqmx/_stubs/nidaqmx_pb2_grpc.pyi
nidaqmx/_time.py
nidaqmx/_waveform_utils.py
nidaqmx/constants.py
nidaqmx/error_codes.py
nidaqmx/errors.py
nidaqmx/grpc_session_options.py
nidaqmx/scale.py
nidaqmx/stream_readers/__init__.py
nidaqmx/stream_readers/_analog_multi_channel_reader.py
nidaqmx/stream_readers/_analog_single_channel_reader.py
nidaqmx/stream_readers/_analog_unscaled_reader.py
nidaqmx/stream_readers/_channel_reader_base.py
nidaqmx/stream_readers/_counter_reader.py
nidaqmx/stream_readers/_digital_multi_channel_reader.py
nidaqmx/stream_readers/_digital_single_channel_reader.py
nidaqmx/stream_readers/_power_readers.py
nidaqmx/stream_writers/__init__.py
nidaqmx/stream_writers/_analog_multi_channel_writer.py
nidaqmx/stream_writers/_analog_single_channel_writer.py
nidaqmx/stream_writers/_analog_unscaled_writer.py
nidaqmx/stream_writers/_channel_writer_base.py
nidaqmx/stream_writers/_counter_writer.py
nidaqmx/stream_writers/_digital_multi_channel_writer.py
nidaqmx/stream_writers/_digital_single_channel_writer.py
nidaqmx/system/__init__.py
nidaqmx/system/_collections/__init__.py
nidaqmx/system/_collections/device_collection.py
nidaqmx/system/_collections/persisted_channel_collection.py
nidaqmx/system/_collections/persisted_scale_collection.py
nidaqmx/system/_collections/persisted_task_collection.py
nidaqmx-1.4.0.dist-info/LICENSE
nidaqmx-1.4.0.dist-info/METADATA
nidaqmx-1.4.0.dist-info/WHEEL
nidaqmx-1.4.0.dist-info/entry_points.txt
nidaqmx-1.4.0.dist-info/RECORD
