Metadata-Version: 2.3
Name: nidaqmx
Version: 1.4.0
Summary: NI-DAQmx Python API
License: MIT
Keywords: nidaqmx,nidaq,daqmx,daq
Author: NI
Author-email: opensource@ni.com
Maintainer: Zach Hindes
Maintainer-email: zach.hindes@ni.com
Requires-Python: >=3.9,<4.0
Classifier: Development Status :: 5 - Production/Stable
Classifier: Intended Audience :: Developers
Classifier: Intended Audience :: Manufacturing
Classifier: Intended Audience :: Science/Research
Classifier: License :: OSI Approved :: MIT License
Classifier: Operating System :: Microsoft :: Windows
Classifier: Operating System :: POSIX
Classifier: Programming Language :: Python :: 3
Classifier: Programming Language :: Python :: 3.9
Classifier: Programming Language :: Python :: 3.10
Classifier: Programming Language :: Python :: 3.11
Classifier: Programming Language :: Python :: 3.12
Classifier: Programming Language :: Python :: 3.13
Classifier: Programming Language :: Python :: 3.14
Classifier: Programming Language :: Python :: Implementation :: CPython
Classifier: Programming Language :: Python :: Implementation :: PyPy
Classifier: Topic :: System :: Hardware :: Hardware Drivers
Provides-Extra: grpc
Requires-Dist: click (>=8.0.0)
Requires-Dist: deprecation (>=2.1)
Requires-Dist: distro (>=1.9.0) ; sys_platform == "linux"
Requires-Dist: grpcio (>=1.49.0,<2.0) ; extra == "grpc"
Requires-Dist: hightime (>=0.2.2)
Requires-Dist: ni-grpcdevice-v1-proto (>=1.0.0) ; extra == "grpc"
Requires-Dist: ni-protobuf-types (>=1.0.0) ; extra == "grpc"
Requires-Dist: nitypes (>=1.0.1)
Requires-Dist: numpy (>=1.22) ; python_version >= "3.9" and python_version < "3.13"
Requires-Dist: numpy (>=2.1) ; python_version >= "3.13" and python_version < "4.0"
Requires-Dist: protobuf (>=4.21) ; extra == "grpc"
Requires-Dist: python-decouple (>=3.8)
Requires-Dist: requests (>=2.25.0)
Requires-Dist: typing_extensions (>=4.0.0)
Requires-Dist: tzlocal (>=5.0,<6.0)
Project-URL: Documentation, https://nidaqmx-python.readthedocs.io
Project-URL: Repository, https://github.com/ni/nidaqmx-python
